CHANGELOG.txt
LICENSE.txt
MANIFEST.in
README.rst
profig.py
setup.cfg
setup.py
tests.py
profig.egg-info/PKG-INFO
profig.egg-info/SOURCES.txt
profig.egg-info/dependency_links.txt
profig.egg-info/top_level.txt