Metadata-Version: 1.1
Name: profig
Version: 0.4.1
Summary: A configuration library.
Home-page: https://bitbucket.org/dhagrow/profig/
Author: Miguel Turner
Author-email: cymrow@gmail.com
License: MIT
Keywords: config,configuration,options,settings
Platform: any
Classifier: Development Status :: 4 - Beta
Classifier: Intended Audience :: Developers
Classifier: License :: OSI Approved :: MIT License
Classifier: Topic :: Software Development :: Libraries
Classifier: Programming Language :: Python :: 2
Classifier: Programming Language :: Python :: 2.7
Classifier: Programming Language :: Python :: 3
Classifier: Programming Language :: Python :: 3.2
Classifier: Programming Language :: Python :: 3.3
Classifier: Programming Language :: Python :: 3.4
